py_terminal_chat/__init__.py
py_terminal_chat/client/__init__.py
py_terminal_chat/client/__main__.py
py_terminal_chat/server/__init__.py
py_terminal_chat/server/__main__.py
py_terminal_chat/server/handler.py
py_terminal_chat/server/stores.py
py_terminal_chat-0.1.0.dist-info/METADATA
py_terminal_chat-0.1.0.dist-info/WHEEL
py_terminal_chat-0.1.0.dist-info/entry_points.txt
py_terminal_chat-0.1.0.dist-info/RECORD
