Metadata-Version: 2.1
Name: py-terminal-chat
Version: 0.1.0
Summary: A simple chat server written in python asyncio including a client gui to run in terminal.
Author: Ahmed Bin Nasser
Author-email: ahmednasser.bin@gmail.com
Requires-Python: >=3.10,<4.0
Classifier: Programming Language :: Python :: 3
Classifier: Programming Language :: Python :: 3.10
Classifier: Programming Language :: Python :: 3.11
Classifier: Programming Language :: Python :: 3.12
